wezbxsrv/__init__.py
wezbxsrv/app.py
wezbxsrv/msgtype_handler/__init__.py
wezbxsrv/msgtype_handler/event_msgtype_handler.py
wezbxsrv/msgtype_handler/text_msgtype_handler.py
wezbxsrv_cfomp-1.0.1.dist-info/METADATA
wezbxsrv_cfomp-1.0.1.dist-info/WHEEL
wezbxsrv_cfomp-1.0.1.dist-info/top_level.txt
wezbxsrv_cfomp-1.0.1.dist-info/RECORD
